modeltrans_tabs/__init__.py
modeltrans_tabs/admin.py
modeltrans_tabs/apps.py
modeltrans_tabs/static/modeltrans_tabs/i18n_tabs.css
modeltrans_tabs/static/modeltrans_tabs/i18n_tabs.js
django_modeltrans_tabs-0.1.1.dist-info/METADATA
django_modeltrans_tabs-0.1.1.dist-info/WHEEL
django_modeltrans_tabs-0.1.1.dist-info/RECORD
