Metadata-Version: 2.1
Name: django-modeltrans-tabs
Version: 0.1.1
Summary: Tabbed UI for django-modeltrans
License: MIT
Author: Julian Wachholz
Author-email: julian@wachholz.ch
Requires-Python: >=3.8,<4.0
Classifier: License :: OSI Approved :: MIT License
Classifier: Programming Language :: Python :: 3
Classifier: Programming Language :: Python :: 3.8
Classifier: Programming Language :: Python :: 3.9
Classifier: Programming Language :: Python :: 3.10
Classifier: Programming Language :: Python :: 3.11
Classifier: Programming Language :: Python :: 3.12
